{"_id":"feat-improved-two-weapon-fighting","name":"Improved Two-Weapon Fighting","type":"feat","img":"icons/svg/sword.svg","system":{"description":"<p>You are skilled at fighting with two weapons.</p>","key":"improvedTwoWeaponFighting","type":"General","fighterBonusEligible":"true","prerequisites":"Dex 17, Two-Weapon Fighting, base attack bonus +6","benefit":"<p>In addition to the standard single extra attack you get with an off-hand weapon, you get a second attack with it, albeit at a -5 penalty.</p>","special":"A fighter may select Improved Two-Weapon Fighting as one of his fighter bonus feats.","scalingTable":[],"prerequisiteFeatKeys":["twoWeaponFighting"],"prerequisiteBAB":6,"prerequisiteAbilityScores":{"str":0,"dex":15,"con":0,"int":0,"wis":0,"cha":0},"prerequisiteFeatUuids":[]},"flags":{},"folder":null,"sort":0}
