{
  "name": "Copper Dragon, Wyrm",
  "type": "npc",
  "img": "icons/svg/mystery-man.svg",
  "system": {
    "key": "monsterCopperDragonWyrm",
    "creatureTypeKey": "dragon",
    "subtypeKeys": [
      "earth"
    ],
    "abilities": {
      "str": {
        "value": 35,
        "racial": 0,
        "mod": 0
      },
      "dex": {
        "value": 10,
        "racial": 0,
        "mod": 0
      },
      "con": {
        "value": 25,
        "racial": 0,
        "mod": 0
      },
      "int": {
        "value": 22,
        "racial": 0,
        "mod": 0
      },
      "wis": {
        "value": 23,
        "racial": 0,
        "mod": 0
      },
      "cha": {
        "value": 22,
        "racial": 0,
        "mod": 0
      }
    },
    "details": {
      "type": "",
      "creatureTypeUuid": "",
      "subtypeUuids": [],
      "cr": "23",
      "alignment": "Chaotic Good",
      "size": "Gargantuan"
    },
    "statBlock": {
      "naturalArmor": 34,
      "space": "20 ft",
      "reach": "15 ft",
      "movement": {
        "land": 40,
        "fly": 200,
        "flyManeuverability": "clumsy",
        "swim": 0,
        "burrow": 0,
        "climb": 0
      },
      "naturalAttacks": [
        {
          "name": "Bite",
          "dice": "4d6",
          "damageType": "piercing",
          "primary": "true",
          "reach": "20 ft",
          "presetAttackBonus": 43
        },
        {
          "name": "Claw",
          "dice": "2d8",
          "damageType": "slashing",
          "primary": "false",
          "reach": "15 ft",
          "presetAttackBonus": 41
        },
        {
          "name": "Claw",
          "dice": "2d8",
          "damageType": "slashing",
          "primary": "false",
          "reach": "15 ft",
          "presetAttackBonus": 41
        },
        {
          "name": "Wing",
          "dice": "2d6",
          "damageType": "bludgeoning",
          "primary": "false",
          "reach": "15 ft",
          "presetAttackBonus": 41
        },
        {
          "name": "Wing",
          "dice": "2d6",
          "damageType": "bludgeoning",
          "primary": "false",
          "reach": "15 ft",
          "presetAttackBonus": 41
        },
        {
          "name": "Tail slap",
          "dice": "2d8",
          "damageType": "bludgeoning",
          "primary": "false",
          "reach": "15 ft",
          "presetAttackBonus": 41
        },
        {
          "name": "Crush",
          "dice": "4d6",
          "damageType": "bludgeoning",
          "primary": "false",
          "reach": "15 ft",
          "presetAttackBonus": 41
        },
        {
          "name": "Tail sweep",
          "dice": "2d6",
          "damageType": "bludgeoning",
          "primary": "false",
          "reach": "15 ft",
          "presetAttackBonus": 41
        }
      ],
      "damageReduction": {
        "value": 20,
        "bypass": "magic"
      },
      "spellResistance": 29,
      "senses": [
        {
          "type": "darkvision",
          "range": "60 ft."
        },
        {
          "type": "lowLight",
          "range": ""
        }
      ],
      "specialAbilities": "<p><strong>Full attack</strong> (SRD true dragon, Multiattack −2 on secondaries): Bite +43, 2× Claw +41, 2× Wing +41, Tail slap +41, Crush +41, Tail sweep +41.</p><p><strong>Breath weapon</strong> (SRD table — save DC in parentheses): Line of acid or cone of slow gas (Fort vs. DC 34; slow duration see SRD). 22d4 acid line.</p><p><strong>Special qualities (by age):</strong> —</p><p>NPC spell lists are not implemented on the sheet yet. Imported from d20srd.org.</p><p><strong>Skills:</strong> Bluff, Hide, and Jump are class skills.</p><p>Casts as sorcerer of indicated CL; also cleric spells from Chaos, Earth, and Trickery domains as arcane (SRD).</p><p><strong>DR 20/magic.</strong> CL 17th.</p>",
      "environment": "Warm hills",
      "organization": "See SRD (solitary or clutch to family by age)",
      "treasure": "Triple standard",
      "advancement": "",
      "levelAdjustment": 0
    },
    "attributes": {
      "hp": {
        "value": 472,
        "max": 472,
        "temp": 0,
        "nonlethal": 0,
        "stable": false
      },
      "ac": {
        "value": 10,
        "touch": 6,
        "flatFooted": 40,
        "misc": 0
      },
      "initiative": {
        "bonus": 0
      },
      "speed": {
        "value": 40
      }
    },
    "saves": {
      "fort": {
        "base": 26,
        "total": 0
      },
      "ref": {
        "base": 19,
        "total": 0
      },
      "will": {
        "base": 25,
        "total": 0
      }
    },
    "combat": {
      "bab": 35,
      "grapple": 0,
      "meleeAttack": {
        "misc": 0,
        "total": 0
      },
      "rangedAttack": {
        "misc": 0,
        "total": 0
      }
    },
    "biography": "<p>Chaotic good true dragons of warm hills; breath is acid line and slowing gas. Copper dragons enjoy wit and riddles.</p>",
    "currency": {
      "pp": 0,
      "gp": 0,
      "sp": 0,
      "cp": 0
    }
  },
  "items": [
    {
      "name": "Bluff",
      "type": "skill",
      "img": "icons/svg/eye.svg",
      "system": {
        "description": "<p>SRD skill.</p>",
        "key": "bluff",
        "ability": "cha",
        "ranks": 31,
        "modifier": {
          "misc": 0,
          "total": 0
        },
        "trainedOnly": "false",
        "armorCheckPenalty": "false",
        "exclusive": "false",
        "npcClassSkill": true
      },
      "flags": {},
      "folder": null,
      "sort": 101
    },
    {
      "name": "Hide",
      "type": "skill",
      "img": "icons/svg/eye.svg",
      "system": {
        "description": "<p>SRD skill.</p>",
        "key": "hide",
        "ability": "dex",
        "ranks": 31,
        "modifier": {
          "misc": 0,
          "total": 0
        },
        "trainedOnly": "false",
        "armorCheckPenalty": "true",
        "exclusive": "false",
        "npcClassSkill": true
      },
      "flags": {},
      "folder": null,
      "sort": 102
    },
    {
      "name": "Jump",
      "type": "skill",
      "img": "icons/svg/eye.svg",
      "system": {
        "description": "<p>SRD skill.</p>",
        "key": "jump",
        "ability": "str",
        "ranks": 31,
        "modifier": {
          "misc": 0,
          "total": 0
        },
        "trainedOnly": "false",
        "armorCheckPenalty": "true",
        "exclusive": "false",
        "npcClassSkill": true
      },
      "flags": {},
      "folder": null,
      "sort": 103
    },
    {
      "name": "Listen",
      "type": "skill",
      "img": "icons/svg/eye.svg",
      "system": {
        "description": "<p>SRD skill.</p>",
        "key": "listen",
        "ability": "wis",
        "ranks": 31,
        "modifier": {
          "misc": 0,
          "total": 0
        },
        "trainedOnly": "false",
        "armorCheckPenalty": "false",
        "exclusive": "false",
        "npcClassSkill": true
      },
      "flags": {},
      "folder": null,
      "sort": 104
    },
    {
      "name": "Spot",
      "type": "skill",
      "img": "icons/svg/eye.svg",
      "system": {
        "description": "<p>SRD skill.</p>",
        "key": "spot",
        "ability": "wis",
        "ranks": 31,
        "modifier": {
          "misc": 0,
          "total": 0
        },
        "trainedOnly": "false",
        "armorCheckPenalty": "false",
        "exclusive": "false",
        "npcClassSkill": true
      },
      "flags": {},
      "folder": null,
      "sort": 105
    }
  ],
  "flags": {},
  "folder": null,
  "sort": 0,
  "prototypeToken": {
    "texture": {
      "src": "icons/svg/mystery-man.svg"
    }
  }
}
