{
  "name": "Hill Giant",
  "type": "npc",
  "img": "icons/svg/mystery-man.svg",
  "system": {
    "key": "monsterHillGiant",
    "creatureTypeKey": "giant",
    "subtypeKeys": [],
    "abilities": {
      "str": {
        "value": 25,
        "racial": 0,
        "mod": 0
      },
      "dex": {
        "value": 8,
        "racial": 0,
        "mod": 0
      },
      "con": {
        "value": 19,
        "racial": 0,
        "mod": 0
      },
      "int": {
        "value": 6,
        "racial": 0,
        "mod": 0
      },
      "wis": {
        "value": 10,
        "racial": 0,
        "mod": 0
      },
      "cha": {
        "value": 7,
        "racial": 0,
        "mod": 0
      }
    },
    "details": {
      "type": "",
      "creatureTypeUuid": "",
      "subtypeUuids": [],
      "cr": "7",
      "alignment": "Chaotic Evil",
      "size": "Large"
    },
    "statBlock": {
      "naturalArmor": 9,
      "space": "10 ft",
      "reach": "10 ft",
      "movement": {
        "land": 0,
        "fly": 0,
        "flyManeuverability": "",
        "swim": 0,
        "burrow": 0,
        "climb": 0
      },
      "naturalAttacks": [
        {
          "name": "Slam",
          "dice": "2d8+10",
          "damageType": "bludgeoning",
          "primary": "true",
          "reach": ""
        }
      ],
      "damageReduction": {
        "value": 0,
        "bypass": ""
      },
      "spellResistance": 0,
      "senses": [],
      "specialAbilities": "<!--thirdera-srd-hub-start:giant.htm--><section class=\"thirdera-srd-hub\" data-hub=\"Giant\"><h4>SRD type: Giant</h4><p>\n\tAll giants speak Giant. Those with Intelligence scores of 10 or higher also speak Common.\n</p>\n\n<h2>Combat</h2>\n<p>\n\tGiants relish melee combat. They favor massive two-handed weapons and wield them with impressive skill. They have enough cunning to soften up a foe with ranged attacks first, if they can. A giant’s favorite ranged weapon is a big rock.\n</p>\n\n<h5>Rock Throwing (<a href=\"/srd/specialAbilities.htm#extraordinaryAbilities\">Ex</a>)</h5>\n<p>\n\tAdult giants are accomplished rock throwers and receive a +1 racial bonus on <a href=\"/srd/combat/combatStatistics.htm#attackRoll\">attack rolls</a> when throwing rocks. A giant of at least Large size can hurl rocks weighing 40 to 50 pounds each (Small objects) up to five range increments. The size of the range increment varies with the giant’s variety. A Huge giant can hurl rocks of 60 to 80 pounds (Medium objects).\n</p>\n\n<h5>Rock Catching (<a href=\"/srd/specialAbilities.htm#extraordinaryAbilities\">Ex</a>)</h5>\n<p>\n\tA giant of at least Large size can catch Small, Medium, or Large rocks (or projectiles of similar shape).\n</p>\n<p>\n\tOnce per round, a giant that would normally be hit by a rock can make a <a href=\"/srd/combat/combatStatistics.htm#reflex\">Reflex save</a> to catch it as a <a href=\"/srd/combat/actionsInCombat.htm#freeActions\">free action</a>. The DC is 15 for a Small rock, 20 for a Medium one, and 25 for a Large one. (If the projectile provides a magical bonus on <a href=\"/srd/combat/combatStatistics.htm#attackRoll\">attack rolls</a>, the DC increases by that amount.) The giant must be ready for and aware of the attack in order to make a rock catching attempt.\n</p></section><!--thirdera-srd-hub-end-->\n<p><strong>Special Attacks:</strong> Rock throwing</p><p><strong>Special Qualities:</strong> Low-light vision, rock catching</p><p>Imported from the d20 SRD; verify attacks and skills in-game. Full rules at d20srd.org.</p>",
      "environment": "Temperate hills",
      "organization": "Solitary, gang (2-5), band (6-9 plus 35% noncombatants), hunting/raiding party (6-9 plus 2-4 dire wolves), or tribe (21-30 plus 35% noncombatants plus 12-30 dire wolves, 2-4 ogres, and 12-22 orcs)",
      "treasure": "Standard",
      "advancement": "By character class",
      "levelAdjustment": 0
    },
    "attributes": {
      "hp": {
        "value": 102,
        "max": 102,
        "temp": 0,
        "nonlethal": 0,
        "stable": false
      },
      "ac": {
        "value": 10,
        "touch": 8,
        "flatFooted": 20,
        "misc": 0
      },
      "initiative": {
        "bonus": -1
      },
      "speed": {
        "value": 30
      }
    },
    "saves": {
      "fort": {
        "base": 12,
        "total": 0
      },
      "ref": {
        "base": 3,
        "total": 0
      },
      "will": {
        "base": 4,
        "total": 0
      }
    },
    "combat": {
      "bab": 9,
      "grapple": 0,
      "meleeAttack": {
        "misc": 0,
        "total": 0
      },
      "rangedAttack": {
        "misc": 0,
        "total": 0
      }
    },
    "biography": "<p>\n\tSkin color among hill giants ranges from light tan to deep ruddy brown. Their hair is brown or black, with eyes the same color. Hill giants wear layers of crudely prepared hides with the fur left on. They seldom wash or repair their garments, preferring to simply add more hides as their old ones wear out.\n</p>\n<p>\n\tAdults are about 10&frac12; feet tall and weigh about 1,100 pounds. Hill giants can live to be 200 years old.\n</p>\n\n<h3>Combat</h3>\n<p>\n\tHill giants prefer to fight from high, rocky outcroppings, where they can pelt opponents with rocks and boulders while limiting the risk to themselves.\n</p>\n<p>\n\tHill giants love to make overrun attacks against smaller creatures when they first join battle. Thereafter, they stand fast and swing away with their massive clubs.\n</p>\n\n<h5>Rock Throwing (Ex)</h5>\n<p>\n\tThe range increment is 120 feet for a hill giant’s thrown rocks.\n</p>",
    "currency": {
      "pp": 0,
      "gp": 0,
      "sp": 0,
      "cp": 0
    },
    "cgsGrants": {
      "senses": [
        {
          "type": "lowLight",
          "range": ""
        }
      ],
      "creatureTypeOverlayUuids": [],
      "subtypeOverlayUuids": []
    }
  },
  "items": [],
  "flags": {
    "thirdera": {
      "srdHubTraits": {
        "hubPath": "giant.htm",
        "hubTitle": "Giant",
        "immunities": [],
        "energyResistance": {},
        "traitFlags": {
          "telepathy": false,
          "summon": false,
          "tongues": false,
          "seeInDarkness": false,
          "planeShift": false,
          "blindsight": false,
          "swarmSubtype": false
        },
        "saveRacialBonuses": [],
        "traitBullets": [],
        "languagesNote": null
      }
    }
  },
  "folder": null,
  "sort": 0,
  "prototypeToken": {
    "texture": {
      "src": "icons/svg/mystery-man.svg"
    }
  }
}
