{
  "name": "Crocodile, Huge",
  "type": "npc",
  "img": "icons/svg/mystery-man.svg",
  "system": {
    "key": "monsterCrocodileHuge",
    "creatureTypeKey": "animal",
    "subtypeKeys": [],
    "abilities": {
      "str": {
        "value": 27,
        "racial": 0,
        "mod": 0
      },
      "dex": {
        "value": 12,
        "racial": 0,
        "mod": 0
      },
      "con": {
        "value": 21,
        "racial": 0,
        "mod": 0
      },
      "int": {
        "value": 1,
        "racial": 0,
        "mod": 0
      },
      "wis": {
        "value": 12,
        "racial": 0,
        "mod": 0
      },
      "cha": {
        "value": 2,
        "racial": 0,
        "mod": 0
      }
    },
    "details": {
      "type": "",
      "creatureTypeUuid": "",
      "subtypeUuids": [],
      "cr": "4",
      "alignment": "True Neutral",
      "size": "Huge"
    },
    "statBlock": {
      "naturalArmor": 7,
      "space": "15 ft",
      "reach": "10 ft",
      "movement": {
        "land": 0,
        "fly": 0,
        "flyManeuverability": "",
        "swim": 30,
        "burrow": 0,
        "climb": 0
      },
      "naturalAttacks": [
        {
          "name": "Bite",
          "dice": "2d8",
          "damageType": "piercing",
          "primary": "true",
          "reach": ""
        }
      ],
      "damageReduction": {
        "value": 0,
        "bypass": ""
      },
      "spellResistance": 0,
      "senses": [
        {
          "type": "lowLight",
          "range": ""
        }
      ],
      "specialAbilities": "<p>As crocodile (improved grab, hold breath, racial Swim).</p>",
      "environment": "Warm marshes",
      "organization": "Solitary or colony",
      "treasure": "None",
      "advancement": "",
      "levelAdjustment": 0
    },
    "attributes": {
      "hp": {
        "value": 85,
        "max": 85,
        "temp": 0,
        "nonlethal": 0,
        "stable": false
      },
      "ac": {
        "value": 10,
        "touch": 9,
        "flatFooted": 15,
        "misc": 0
      },
      "initiative": {
        "bonus": 0
      },
      "speed": {
        "value": 20
      }
    },
    "saves": {
      "fort": {
        "base": 9,
        "total": 0
      },
      "ref": {
        "base": 5,
        "total": 0
      },
      "will": {
        "base": 3,
        "total": 0
      }
    },
    "combat": {
      "bab": 6,
      "grapple": 0,
      "meleeAttack": {
        "misc": 5,
        "total": 0
      },
      "rangedAttack": {
        "misc": 0,
        "total": 0
      }
    },
    "biography": "<p>Massive crocodilians exceeding 20 feet.</p>",
    "currency": {
      "pp": 0,
      "gp": 0,
      "sp": 0,
      "cp": 0
    }
  },
  "items": [
    {
      "name": "Alertness",
      "type": "feat",
      "img": "icons/svg/eye.svg",
      "system": {
        "description": "<p>You are particularly observant.</p>",
        "key": "alertness",
        "type": "General",
        "prerequisites": "",
        "benefit": "<p>You get a +2 bonus on all Listen checks and Spot checks.</p>",
        "special": "",
        "scalingTable": [],
        "prerequisiteFeatKeys": [],
        "prerequisiteBAB": 0,
        "prerequisiteAbilityScores": {
          "str": 0,
          "dex": 0,
          "con": 0,
          "int": 0,
          "wis": 0,
          "cha": 0
        },
        "prerequisiteFeatUuids": [],
        "changes": [
          {
            "key": "skill.listen",
            "value": 2
          },
          {
            "key": "skill.spot",
            "value": 2
          }
        ]
      },
      "flags": {},
      "folder": null,
      "sort": 0
    },
    {
      "name": "Endurance",
      "type": "feat",
      "img": "icons/svg/shield.svg",
      "system": {
        "description": "<p>You have enhanced physical stamina.</p>",
        "key": "endurance",
        "type": "General",
        "prerequisites": "",
        "benefit": "<p>You gain a +4 bonus on the following checks and saves: Swim checks made to resist nonlethal damage from exhaustion; Constitution checks made to continue running; Constitution checks made to avoid nonlethal damage from a forced march; Constitution checks made to hold your breath; Constitution checks made to avoid nonlethal damage from starvation or thirst; Fortitude saves made to avoid nonlethal damage from hot or cold environments; and Fortitude saves made to resist damage from suffocation.</p><p>Also, you may sleep in light or medium armor without becoming fatigued.</p>",
        "special": "A ranger automatically gains Endurance as a bonus feat at 3rd level. He need not select it.",
        "scalingTable": [],
        "prerequisiteFeatKeys": [],
        "prerequisiteBAB": 0,
        "prerequisiteAbilityScores": {
          "str": 0,
          "dex": 0,
          "con": 0,
          "int": 0,
          "wis": 0,
          "cha": 0
        },
        "prerequisiteFeatUuids": []
      },
      "flags": {},
      "folder": null,
      "sort": 0
    },
    {
      "name": "Hide",
      "type": "skill",
      "img": "icons/svg/eye.svg",
      "system": {
        "description": "<p>SRD skill.</p>",
        "key": "hide",
        "ability": "dex",
        "ranks": 2,
        "modifier": {
          "misc": 0,
          "total": 0
        },
        "trainedOnly": "false",
        "armorCheckPenalty": "true",
        "exclusive": "false",
        "npcClassSkill": true
      },
      "flags": {},
      "folder": null,
      "sort": 101
    },
    {
      "name": "Listen",
      "type": "skill",
      "img": "icons/svg/eye.svg",
      "system": {
        "description": "<p>SRD skill.</p>",
        "key": "listen",
        "ability": "wis",
        "ranks": 4,
        "modifier": {
          "misc": 0,
          "total": 0
        },
        "trainedOnly": "false",
        "armorCheckPenalty": "false",
        "exclusive": "false",
        "npcClassSkill": true
      },
      "flags": {},
      "folder": null,
      "sort": 102
    },
    {
      "name": "Spot",
      "type": "skill",
      "img": "icons/svg/eye.svg",
      "system": {
        "description": "<p>SRD skill.</p>",
        "key": "spot",
        "ability": "wis",
        "ranks": 4,
        "modifier": {
          "misc": 0,
          "total": 0
        },
        "trainedOnly": "false",
        "armorCheckPenalty": "false",
        "exclusive": "false",
        "npcClassSkill": true
      },
      "flags": {},
      "folder": null,
      "sort": 103
    },
    {
      "name": "Swim",
      "type": "skill",
      "img": "icons/svg/eye.svg",
      "system": {
        "description": "<p>SRD skill.</p>",
        "key": "swim",
        "ability": "str",
        "ranks": 4,
        "modifier": {
          "misc": 8,
          "total": 0
        },
        "trainedOnly": "false",
        "armorCheckPenalty": "false",
        "exclusive": "false",
        "npcClassSkill": true
      },
      "flags": {},
      "folder": null,
      "sort": 104
    }
  ],
  "flags": {},
  "folder": null,
  "sort": 0,
  "prototypeToken": {
    "texture": {
      "src": "icons/svg/mystery-man.svg"
    }
  }
}
