{"name":"Darkvision","type":"spell","img":"icons/svg/aura.svg","system":{"description":"<p>The subject gains the ability to see 60 feet even in total darkness. Darkvision is black and white only but otherwise like normal sight. Darkvision does not grant one the ability to see in magical darkness. Darkvision can be made permanent with a permanency spell.</p>","level":2,"levelsByClass":[{"classKey":"sorcererWizard","className":"Sorcerer/Wizard","level":2}],"levelsByDomain":[],"schoolKey":"transmutation","schoolName":"Transmutation","schoolSubschool":"","schoolDescriptors":[],"components":{"verbal":"true","somatic":"true","material":"true","focus":"false","divineFocus":"false","xp":0,"materialDescription":"Either a pinch of dried carrot or an agate"},"castingTime":"1 standard action","range":"Touch","target":"Creature touched","duration":"1 hour/level","savingThrow":"Will negates (harmless)","spellResistance":"yes-harmless","prepared":0,"cast":0},"flags":{},"folder":null,"sort":119}
