{"name":"Astral Projection","type":"spell","img":"icons/svg/aura.svg","system":{"description":"<p>Project astral body onto Astral Plane; body in suspended animation. Silver cord links astral to body; if broken you die. Can travel to other planes; form new body there. Companions linked in circle come with you. Lasts until you end it or dispel/cord broken/body destroyed.</p>","level":9,"levelsByClass":[{"classKey":"cleric","className":"Cleric","level":9},{"classKey":"sorcererWizard","className":"Sorcerer/Wizard","level":9}],"levelsByDomain":[{"domainKey":"travel","domainName":"Travel","level":9}],"schoolKey":"necromancy","schoolName":"Necromancy","schoolSubschool":"","schoolDescriptors":[],"components":{"verbal":"true","somatic":"true","material":"true","focus":"false","divineFocus":"false","xp":0,"materialDescription":"Jacinth 1,000 gp plus silver bar 5 gp per person."},"castingTime":"30 minutes","range":"Touch","target":"You plus one willing creature per 2 levels","duration":"See text","savingThrow":"None","spellResistance":"yes","prepared":0,"cast":0},"flags":{},"folder":null,"sort":0}
