{"name":"Inflict Moderate Wounds","type":"spell","img":"icons/svg/aura.svg","system":{"description":"<p>Touch attack, 2d8 damage +1/level (max +10).</p>","level":2,"levelsByClass":[{"classKey":"cleric","className":"Cleric","level":2}],"levelsByDomain":[],"schoolKey":"necromancy","schoolName":"Necromancy","schoolSubschool":"","schoolDescriptors":[],"components":{"verbal":"true","somatic":"true","material":"false","focus":"false","divineFocus":"true","xp":0,"materialDescription":""},"castingTime":"1 standard action","range":"Touch","target":"Creature touched","duration":"Instantaneous","savingThrow":"Will half","spellResistance":"see-text","prepared":0,"cast":0},"flags":{},"folder":null,"sort":149}