{
  "_id": "weapon-trident",
  "name": "Trident",
  "type": "weapon",
  "img": "icons/svg/sword.svg",
  "system": {
    "description": "<p>A trident is a three-pronged spear.</p>",
    "damage": {
      "dice": "1d8",
      "type": "piercing"
    },
    "critical": {
      "range": 20,
      "multiplier": 2
    },
    "range": 0,
    "properties": {
      "melee": "melee",
      "handedness": "oneHanded",
      "size": "Medium",
      "proficiency": "martial"
    },
    "cost": 15,
    "weight": 4,
    "quantity": 1,
    "equipped": "none",
    "containerId": ""
  },
  "flags": {},
  "folder": null,
  "sort": 0
}
